README.rst
setup.py
dwdweather/__init__.py
dwdweather/client.py
dwdweather/commands.py
dwdweather/core.py
dwdweather/knowledge.py
dwdweather/util.py
dwdweather2.egg-info/PKG-INFO
dwdweather2.egg-info/SOURCES.txt
dwdweather2.egg-info/dependency_links.txt
dwdweather2.egg-info/entry_points.txt
dwdweather2.egg-info/requires.txt
dwdweather2.egg-info/top_level.txt
tests/__init__.py
tests/test_dwdweather.py